mohflow/__init__.py
mohflow/auto_config.py
mohflow/cli.py
mohflow/config.py
mohflow/config_loader.py
mohflow/exceptions.py
mohflow/framework_detection.py
mohflow/static_config.py
mohflow/types.py
mohflow/config/hot_reload.py
mohflow/context/__init__.py
mohflow/context/correlation.py
mohflow/context/enrichment.py
mohflow/context/filters.py
mohflow/context/scoped_context.py
mohflow/formatters/__init__.py
mohflow/formatters/orjson_formatter.py
mohflow/formatters/structured_formatter.py
mohflow/handlers/__init__.py
mohflow/handlers/async_handlers.py
mohflow/handlers/loki.py
mohflow/integrations/__init__.py
mohflow/integrations/asgi_wsgi.py
mohflow/integrations/celery.py
mohflow/integrations/django.py
mohflow/integrations/fastapi.py
mohflow/integrations/flask.py
mohflow/logger/__init__.py
mohflow/logger/base.py
mohflow/metrics/__init__.py
mohflow/metrics/auto_metrics.py
mohflow/opentelemetry/__init__.py
mohflow/opentelemetry/exporters.py
mohflow/opentelemetry/propagators.py
mohflow/opentelemetry/trace_integration.py
mohflow/privacy/__init__.py
mohflow/privacy/compliance_reporter.py
mohflow/privacy/pii_detector.py
mohflow/privacy/privacy_filter.py
mohflow/sampling/__init__.py
mohflow/sampling/adaptive_sampler.py
mohflow/templates/__init__.py
mohflow/templates/template_manager.py
mohflow-1.1.2.dist-info/licenses/LICENSE
mohflow-1.1.2.dist-info/METADATA
mohflow-1.1.2.dist-info/WHEEL
mohflow-1.1.2.dist-info/entry_points.txt
mohflow-1.1.2.dist-info/top_level.txt
mohflow-1.1.2.dist-info/RECORD
