Metadata-Version: 2.4
Name: mohflow
Version: 1.1.2
Summary: Simple, powerful logging for Python applications
Author-email: Parijat Mukherjee <parijat_mukherjee@live.com>
License: MIT License
Project-URL: Wiki, https://github.com/parijatmukherjee/mohflow/wiki
Project-URL: Repository, https://github.com/parijatmukherjee/mohflow.git
Classifier: Development Status :: 3 - Alpha
Classifier: Intended Audience :: Developers
Classifier: License :: OSI Approved :: MIT License
Classifier: Programming Language :: Python :: 3
Classifier: Programming Language :: Python :: 3.8
Classifier: Programming Language :: Python :: 3.9
Classifier: Programming Language :: Python :: 3.10
Classifier: Programming Language :: Python :: 3.11
Requires-Python: >=3.8
License-File: LICENSE
Requires-Dist: python-logging-loki>=0.3.1
Requires-Dist: python-json-logger>=2.0.0
Requires-Dist: pydantic>=2.0.0
Requires-Dist: pydantic-settings>=2.0.0
Requires-Dist: requests>=2.25.0
Requires-Dist: orjson>=3.8.0
Requires-Dist: opentelemetry-api>=1.20.0
Requires-Dist: opentelemetry-sdk>=1.20.0
Provides-Extra: dev
Requires-Dist: pytest>=7.0.0; extra == "dev"
Requires-Dist: pytest-cov>=4.1.0; extra == "dev"
Requires-Dist: pytest-mock>=3.10.0; extra == "dev"
Requires-Dist: black>=23.0.0; extra == "dev"
Requires-Dist: flake8>=6.0.0; extra == "dev"
Requires-Dist: build>=1.0.0; extra == "dev"
Requires-Dist: twine>=4.0.0; extra == "dev"
Requires-Dist: pytest-asyncio>=0.21.0; extra == "dev"
Requires-Dist: mypy>=1.5.0; extra == "dev"
Requires-Dist: types-requests>=2.25.0; extra == "dev"
Requires-Dist: types-setuptools>=57.0.0; extra == "dev"
Provides-Extra: otel
Requires-Dist: opentelemetry-instrumentation>=0.41b0; extra == "otel"
Requires-Dist: opentelemetry-exporter-jaeger>=1.20.0; extra == "otel"
Requires-Dist: opentelemetry-exporter-otlp>=1.20.0; extra == "otel"
Requires-Dist: opentelemetry-propagator-b3>=1.20.0; extra == "otel"
Requires-Dist: opentelemetry-propagator-jaeger>=1.20.0; extra == "otel"
Provides-Extra: all
Requires-Dist: mohflow[otel]; extra == "all"
Requires-Dist: psutil>=5.9.0; extra == "all"
Requires-Dist: loguru>=0.7.0; extra == "all"
Requires-Dist: structlog>=23.0.0; extra == "all"
Dynamic: license-file
